torchsynth/__info__.py
torchsynth/__init__.py
torchsynth/config.py
torchsynth/module.py
torchsynth/parameter.py
torchsynth/profile.py
torchsynth/signal.py
torchsynth/synth.py
torchsynth/util.py
torchsynth/nebulae/voice/default.json
torchsynth/nebulae/voice/drum.json
torchsynth-1.0.2.dist-info/LICENSE
torchsynth-1.0.2.dist-info/METADATA
torchsynth-1.0.2.dist-info/WHEEL
torchsynth-1.0.2.dist-info/entry_points.txt
torchsynth-1.0.2.dist-info/top_level.txt
torchsynth-1.0.2.dist-info/RECORD
