Metadata-Version: 2.1
Name: torchsynth
Version: 1.0.2
Summary: A modular synthesizer in pytorch, GPU-optional and differentiable
Home-page: https://github.com/torchsynth/torchsynth
Download-URL: https://github.com/torchsynth/torchsynth/
Author: Jordie Shier, Joseph Turian, Max Henry
Author-email: firstnamelastname@gmail.com
License: Apache-2.0
Project-URL: Bug Tracker, https://github.com/torchsynth/torchsynth/issues
Project-URL: Documentation, https://torchsynth.rtfd.io/en/latest/
Project-URL: Source Code, https://github.com/torchsynth/torchsynth/
Classifier: Environment :: Console
Classifier: Environment :: GPU
Classifier: Natural Language :: English
Classifier: Development Status :: 4 - Beta
Classifier: Intended Audience :: Developers
Classifier: Intended Audience :: Science/Research
Classifier: Topic :: Scientific/Engineering :: Artificial Intelligence
Classifier: Topic :: Scientific/Engineering :: Information Analysis
Classifier: Topic :: Multimedia :: Sound/Audio
Classifier: Topic :: Multimedia :: Sound/Audio :: Sound Synthesis
Classifier: License :: OSI Approved :: Apache Software License
Classifier: Operating System :: OS Independent
Classifier: Programming Language :: Python :: 3
Classifier: Programming Language :: Python :: 3.7
Classifier: Programming Language :: Python :: 3.8
Classifier: Programming Language :: Python :: 3.9
Requires-Python: >=3.7
License-File: LICENSE
Requires-Dist: numpy
Requires-Dist: scipy
Requires-Dist: torch (>=1.8)
Requires-Dist: pytorch-lightning (>=1.4)
Provides-Extra: dev
Requires-Dist: pre-commit ; extra == 'dev'
Requires-Dist: nbstripout (==0.3.9) ; extra == 'dev'
Requires-Dist: black (==20.8b1) ; extra == 'dev'
Requires-Dist: jupytext (==v1.10.3) ; extra == 'dev'
Requires-Dist: pytest ; extra == 'dev'
Requires-Dist: pytest-cov ; extra == 'dev'
Requires-Dist: ipython ; extra == 'dev'
Requires-Dist: librosa ; extra == 'dev'
Requires-Dist: scikit-learn (>=0.24.2) ; extra == 'dev'
Requires-Dist: matplotlib ; extra == 'dev'
Requires-Dist: numba (>=0.49.0) ; extra == 'dev'
Requires-Dist: pygments (>=2.7.4) ; extra == 'dev'
Requires-Dist: pytest-env ; extra == 'dev'
Requires-Dist: sphinx (>=3.0.4) ; extra == 'dev'
Requires-Dist: unofficial-pt-lightning-sphinx-theme ; extra == 'dev'
Requires-Dist: MarkupSafe (<2.1.0) ; extra == 'dev'
Requires-Dist: sphinxcontrib-napoleon ; extra == 'dev'
Requires-Dist: sphinx-autodoc-typehints ; extra == 'dev'
Requires-Dist: mock ; extra == 'dev'
Requires-Dist: sphinx-rtd-theme ; extra == 'dev'
Requires-Dist: myst-parser ; extra == 'dev'
Requires-Dist: linkify-it-py ; extra == 'dev'
Provides-Extra: test
Requires-Dist: pytest ; extra == 'test'
Requires-Dist: pytest-cov ; extra == 'test'
Requires-Dist: pygments (>=2.7.4) ; extra == 'test'
Requires-Dist: pytest-env ; extra == 'test'
